pardal-0.1.1.dist-info/licenses/LICENSE
pcb_tool/__init__.py
pcb_tool/__main__.py
pcb_tool/cli.py
pcb_tool/command_history.py
pcb_tool/command_parser.py
pcb_tool/commands.py
pcb_tool/data_model.py
pcb_tool/drc.py
pcb_tool/finalize.py
pcb_tool/footprint_library.py
pcb_tool/kicad_loader.py
pcb_tool/kicad_postprocess.py
pcb_tool/kicad_sdk_writer.py
pcb_tool/kicad_writer.py
pcb_tool/messages.py
pcb_tool/netlist_reader.py
pcb_tool/repl.py
pcb_tool/routing/__init__.py
pcb_tool/routing/constraints.py
pcb_tool/routing/crossing_detector.py
pcb_tool/routing/grid.py
pcb_tool/routing/iterative_router.py
pcb_tool/routing/layer_optimizer.py
pcb_tool/routing/lazy_constraints.py
pcb_tool/routing/multi_net_router.py
pcb_tool/routing/net_order_optimizer.py
pcb_tool/routing/path_connector.py
pcb_tool/routing/pathfinder.py
pcb_tool/routing/via_placer.py
pcb_tool/routing/z3_router.py
pardal-0.1.1.dist-info/METADATA
pardal-0.1.1.dist-info/WHEEL
pardal-0.1.1.dist-info/entry_points.txt
pardal-0.1.1.dist-info/top_level.txt
pardal-0.1.1.dist-info/RECORD
