Metadata-Version: 2.4
Name: pardal
Version: 0.1.1
Summary: A command-line PCB place & route tool with autorouting and DRC.
License: GNU AFFERO GENERAL PUBLIC LICENSE
Requires-Python: >=3.10
License-File: LICENSE
Requires-Dist: z3-solver==4.12.6.0
Dynamic: license-file
